app.py
catch_me-0.3.0.dist-info/entry_points.txt
catch_me-0.3.0.dist-info/METADATA
catch_me-0.3.0.dist-info/WHEEL
catch_me-0.3.0.dist-info/RECORD
